retrymax/__init__.py
retrymax/retry.py
retrymax-0.1.2.dist-info/licenses/LICENSE
retrymax-0.1.2.dist-info/METADATA
retrymax-0.1.2.dist-info/WHEEL
retrymax-0.1.2.dist-info/top_level.txt
retrymax-0.1.2.dist-info/RECORD
