Metadata-Version: 2.4
Name: retrymax
Version: 0.1.2
Summary: Tiny retry decorator for sync and async Python functions
Author-email: veliqq <veliqorg@proton.me>
License: MIT
Project-URL: Homepage, https://github.com/veliqq/retrymax
Project-URL: Repository, https://github.com/veliqq/retrymax
Classifier: Programming Language :: Python :: 3
Classifier: License :: OSI Approved :: MIT License
Classifier: Operating System :: OS Independent
Requires-Python: >=3.8
License-File: LICENSE
Dynamic: license-file
